setup.py
pySigfox/__init__.py
pySigfox/pySigfox.py
pySigfox.egg-info/PKG-INFO
pySigfox.egg-info/SOURCES.txt
pySigfox.egg-info/dependency_links.txt
pySigfox.egg-info/requires.txt
pySigfox.egg-info/top_level.txt