Metadata-Version: 1.1
Name: pySigfox
Version: 0.1.0.dev1
Summary: Connect to Sigfox REST API from Python. This is absolutely NOT OFFICIAL package!!
Home-page: http://www.github.com/hecko/pySigfox
Author: Marcel Hecko
Author-email: maco@blava.net
License: UNKNOWN
Platform: UNKNOWN
Classifier: Development Status :: 3 - Alpha
Classifier: Programming Language :: Python :: 2.7
